biosystfiles/__init__.py
biosystfiles/biosystfiles.py
biosystfiles/create.py
biosystfiles/edit.py
python_biosystfiles-0.0.1.dist-info/LICENSE
python_biosystfiles-0.0.1.dist-info/METADATA
python_biosystfiles-0.0.1.dist-info/WHEEL
python_biosystfiles-0.0.1.dist-info/top_level.txt
python_biosystfiles-0.0.1.dist-info/RECORD
