Metadata-Version: 2.1
Name: python-biosystfiles
Version: 0.0.1
Summary: Reading and editing Biosyst files in Python
Home-page: https://github.com/jkemppainen/biosystfiles
Author: Joni Kemppainen
Author-email: jjtkemppainen1@sheffield.ac.uk
License: UNKNOWN
Platform: UNKNOWN
Classifier: Programming Language :: Python :: 3
Classifier: License :: OSI Approved :: GNU General Public License v3 (GPLv3) 
Classifier: Operating System :: OS Independent
Requires-Python: >=3.0
Requires-Dist: numpy
Requires-Dist: scipy
